charisius/__init__.py
charisius/fullLib.py
charisius-0.0.1.dist-info/LICENSE
charisius-0.0.1.dist-info/METADATA
charisius-0.0.1.dist-info/WHEEL
charisius-0.0.1.dist-info/top_level.txt
charisius-0.0.1.dist-info/RECORD
