Metadata-Version: 2.1
Name: charisius
Version: 0.0.1
Summary: Highly-Optimized, PyTorch implementation of Byzantine-resilient Federated Learning Algorithms
Home-page: https://www.serhanyilmaz.org/Project-Charisius/
Author: Serhan YILMAZ
Author-email: srhnylmz14@gmail.com
License: UNKNOWN
Platform: UNKNOWN
Classifier: Programming Language :: Python :: 3
Classifier: License :: OSI Approved :: MIT License
Classifier: Operating System :: OS Independent
Requires-Python: >=3.6
License-File: LICENSE
